kokos_activator_api/__init__.py
kokos_activator_api/client.py
kokos_activator_api/core/__init__.py
kokos_activator_api/core/api_error.py
kokos_activator_api/core/client_wrapper.py
kokos_activator_api/core/datetime_utils.py
kokos_activator_api/core/file.py
kokos_activator_api/core/force_multipart.py
kokos_activator_api/core/http_client.py
kokos_activator_api/core/http_response.py
kokos_activator_api/core/jsonable_encoder.py
kokos_activator_api/core/pydantic_utilities.py
kokos_activator_api/core/query_encoder.py
kokos_activator_api/core/remove_none_from_dict.py
kokos_activator_api/core/request_options.py
kokos_activator_api/core/serialization.py
kokos_activator_api/database/__init__.py
kokos_activator_api/database/client.py
kokos_activator_api/database/raw_client.py
kokos_activator_api/database/types/__init__.py
kokos_activator_api/database/types/database_inventory.py
kokos_activator_api/database/types/download_codes_request.py
kokos_activator_api/database/types/string_denomination.py
kokos_activator_api/database/types/upload_codes_response.py
kokos_activator_api/database/types/upload_pack.py
kokos_activator_api/environment.py
kokos_activator_api/history/__init__.py
kokos_activator_api/history/client.py
kokos_activator_api/history/errors/__init__.py
kokos_activator_api/history/errors/activation_not_found_error.py
kokos_activator_api/history/raw_client.py
kokos_activator_api/history/types/__init__.py
kokos_activator_api/history/types/get_activation_history_response.py
kokos_activator_api/history/types/short_receipt.py
kokos_activator_api/history/types/stats_response.py
kokos_activator_api/py.typed
kokos_activator_api/redeem/__init__.py
kokos_activator_api/redeem/client.py
kokos_activator_api/redeem/errors/__init__.py
kokos_activator_api/redeem/errors/activation_error_response.py
kokos_activator_api/redeem/errors/character_not_found_error.py
kokos_activator_api/redeem/errors/code_not_found_error.py
kokos_activator_api/redeem/errors/request_error.py
kokos_activator_api-1.0.1.dist-info/METADATA
kokos_activator_api-1.0.1.dist-info/WHEEL
kokos_activator_api-1.0.1.dist-info/RECORD
